README.rst
setup.cfg
setup.py
fs_basespace/__init__.py
fs_basespace/_basespacefs.py
fs_basespace/api_factory.py
fs_basespace/basespace_context.py
fs_basespace/opener.py
fs_basespace.egg-info/PKG-INFO
fs_basespace.egg-info/SOURCES.txt
fs_basespace.egg-info/dependency_links.txt
fs_basespace.egg-info/entry_points.txt
fs_basespace.egg-info/requires.txt
fs_basespace.egg-info/top_level.txt
tests/__init__.py
tests/test_basespace.py