Metadata-Version: 2.1
Name: fs-basespace
Version: 1.4.2
Summary: Illumina Basespace filesystem for PyFilesystem2
Home-page: https://github.com/emedgene/fs_basespace
Download-URL: https://github.com/emedgene/fs_basespace/tarball/0.2.0
Author: emedgene
Author-email: pypi@emedgene.com
License: MIT
Keywords: pyfilesystem,Illumina,Basespace
Platform: any
Classifier: Development Status :: 4 - Beta
Classifier: Intended Audience :: Developers
Classifier: Operating System :: OS Independent
Classifier: Programming Language :: Python
Classifier: Programming Language :: Python :: 2.7
Classifier: Programming Language :: Python :: 3.3
Classifier: Programming Language :: Python :: 3.4
Classifier: Programming Language :: Python :: 3.5
Classifier: Programming Language :: Python :: 3.6
Classifier: Programming Language :: Python :: 3.7
Classifier: Topic :: System :: Filesystems
